<?xml version="1.0" encoding="UTF-8"?>

<databaseChangeLog
        xmlns="http://www.liquibase.org/xml/ns/dbchangelog"
        xmlns:xsi="http://www.w3.org/2001/XMLSchema-instance"
        xmlns:ext="http://www.liquibase.org/xml/ns/dbchangelog-ext"
        xsi:schemaLocation="http://www.liquibase.org/xml/ns/dbchangelog http://www.liquibase.org/xml/ns/dbchangelog/dbchangelog-3.2.xsd
        http://www.liquibase.org/xml/ns/dbchangelog-ext http://www.liquibase.org/xml/ns/dbchangelog/dbchangelog-ext.xsd">

    <changeSet id="1-4" author="xonix">
        <createTable tableName="chart_task">
            <column name="id" type="BIGINT" autoIncrement="true"><constraints primaryKey="true" nullable="false"/></column>
            <column name="descriptor" type="VARCHAR(500)"><constraints unique="true" nullable="false"/></column>
            <column name="forumId" type="VARCHAR(20)"><constraints nullable="false"/></column>
            <column name="nicks" type="VARCHAR(256)"><constraints nullable="false"/></column>
            <column name="start" type="DATETIME"><constraints nullable="false"/></column>
            <column name="end" type="DATETIME"><constraints nullable="false"/></column>
            <column name="type" type="VARCHAR(20)"><constraints nullable="false"/></column>
            <column name="result" type="TEXT"></column>
            <column name="error" type="TEXT"></column>
            <column name="status" type="TEXT"><constraints nullable="false"/></column>
        </createTable>

        <sql>ALTER TABLE chart_task CONVERT TO CHARACTER SET cp1251</sql>
    </changeSet>

    <changeSet id="2" author="xonix">
        <sql>
            ALTER TABLE chart_task MODIFY COLUMN nicks VARCHAR(256) NULL;
            ALTER TABLE chart_task ADD COLUMN queries VARCHAR(256) NULL;
        </sql>
    </changeSet>

    <changeSet id="3" author="xonix">
        <sql>
            delete from zlo_topics where isNew = 0;
        </sql>
    </changeSet>

</databaseChangeLog>